cancel_scope/__init__.py
cancel_scope-1.0.3.dist-info/METADATA
cancel_scope-1.0.3.dist-info/WHEEL
cancel_scope-1.0.3.dist-info/top_level.txt
cancel_scope-1.0.3.dist-info/RECORD
