Metadata-Version: 2.1
Name: cancel-scope
Version: 1.0.3
Summary: Async/Sync cancellation scope context manager
Home-page: https://github.com/ConnorSMaynes/cancel_scope
Author: Connor Sherwood Maynes
Author-email: connormaynes@gmail.com
License: MIT
Keywords: scope,cancel
Classifier: Programming Language :: Python :: 3
Classifier: Operating System :: OS Independent
Requires-Python: >=3.5
